{
    "object_alias": "exface.Core.OBJECT",
    "columns": [
        {
            "name": "_EXPORT_SUMMARY",
            "hidden": true,
            "attribute_alias": "LABEL"
        },
        {
            "name": "CREATED_ON",
            "attribute_alias": "CREATED_ON"
        },
        {
            "name": "MODIFIED_ON",
            "attribute_alias": "MODIFIED_ON"
        },
        {
            "name": "CREATED_BY_USER",
            "attribute_alias": "CREATED_BY_USER"
        },
        {
            "name": "MODIFIED_BY_USER",
            "attribute_alias": "MODIFIED_BY_USER"
        },
        {
            "name": "UID",
            "attribute_alias": "UID"
        },
        {
            "name": "READABLE_FLAG",
            "attribute_alias": "READABLE_FLAG"
        },
        {
            "name": "WRITABLE_FLAG",
            "attribute_alias": "WRITABLE_FLAG"
        },
        {
            "name": "COMMENTS",
            "attribute_alias": "COMMENTS"
        },
        {
            "name": "DOCS",
            "attribute_alias": "DOCS"
        },
        {
            "name": "NAME",
            "attribute_alias": "NAME"
        },
        {
            "name": "INHERIT_DATA_SOURCE_BASE_OBJECT",
            "attribute_alias": "INHERIT_DATA_SOURCE_BASE_OBJECT"
        },
        {
            "name": "DATA_SOURCE",
            "attribute_alias": "DATA_SOURCE"
        },
        {
            "name": "APP",
            "attribute_alias": "APP"
        },
        {
            "name": "SHORT_DESCRIPTION",
            "attribute_alias": "SHORT_DESCRIPTION"
        },
        {
            "name": "PARENT_OBJECT",
            "attribute_alias": "PARENT_OBJECT"
        },
        {
            "name": "DATA_ADDRESS_PROPS",
            "attribute_alias": "DATA_ADDRESS_PROPS"
        },
        {
            "name": "DEFAULT_EDITOR_UXON",
            "attribute_alias": "DEFAULT_EDITOR_UXON"
        },
        {
            "name": "ALIAS",
            "attribute_alias": "ALIAS"
        },
        {
            "name": "DATA_ADDRESS",
            "attribute_alias": "DATA_ADDRESS"
        }
    ],
    "rows": [
        {
            "_EXPORT_SUMMARY": "Web message [axenox.ETL.webservice_request]",
            "CREATED_ON": "2023-10-18 16:06:50",
            "MODIFIED_ON": "2024-10-30 12:22:29",
            "CREATED_BY_USER": "0x31000000000000000000000000000000",
            "MODIFIED_BY_USER": "0x31000000000000000000000000000000",
            "UID": "0x11eeae4695964d78ae46025041000001",
            "READABLE_FLAG": 1,
            "WRITABLE_FLAG": 1,
            "COMMENTS": "",
            "DOCS": "",
            "NAME": "Web request",
            "INHERIT_DATA_SOURCE_BASE_OBJECT": 1,
            "DATA_SOURCE": "0x32000000000000000000000000000000",
            "APP": "0x11ebbc50679eacdabc50025041000001",
            "SHORT_DESCRIPTION": "",
            "PARENT_OBJECT": null,
            "DATA_ADDRESS_PROPS": null,
            "DEFAULT_EDITOR_UXON": {
                "widget_type": "Dialog",
                "readonly": true,
                "widgets": [
                    {
                        "widget_type": "Tabs",
                        "tabs": [
                            {
                                "caption": "HTTP",
                                "widgets": [
                                    {
                                        "widget_type": "WidgetGroup",
                                        "caption": "Request",
                                        "widgets": [
                                            {
                                                "attribute_alias": "CREATED_ON"
                                            },
                                            {
                                                "attribute_alias": "CREATED_BY_USER__LABEL"
                                            },
                                            {
                                                "attribute_alias": "url_path"
                                            },
                                            {
                                                "attribute_alias": "http_method"
                                            },
                                            {
                                                "attribute_alias": "http_content_type"
                                            }
                                        ]
                                    },
                                    {
                                        "widget_type": "WidgetGroup",
                                        "caption": "Response",
                                        "widgets": [
                                            {
                                                "attribute_alias": "webservice_response__http_response_code"
                                            },
                                            {
                                                "attribute_alias": "webservice_response__status"
                                            }
                                        ]
                                    },
                                    {
                                        "widget_type": "WidgetGroup",
                                        "caption": "Flow",
                                        "widgets": [
                                            {
                                                "attribute_alias": "flow_run__flow__LABEL"
                                            },
                                            {
                                                "attribute_alias": "flow_run",
                                                "caption": "Flow run UID"
                                            },
                                            {
                                                "attribute_alias": "flow_run__duration"
                                            }
                                        ]
                                    },
                                    {
                                        "widget_type": "WidgetGroup",
                                        "caption": "Error",
                                        "widgets": [
                                            {
                                                "attribute_alias": "error_logid"
                                            },
                                            {
                                                "attribute_alias": "error_message"
                                            }
                                        ]
                                    }
                                ]
                            },
                            {
                                "caption": "Headers",
                                "widgets": [
                                    {
                                        "value": "Request Header",
                                        "widget_type": "TextHeading",
                                        "heading_level": 3
                                    },
                                    {
                                        "height": "50%",
                                        "width": "max",
                                        "attribute_alias": "http_headers",
                                        "widget_type": "InputJson",
                                        "disabled": true,
                                        "hide_caption": true
                                    },
                                    {
                                        "value": "Response Header",
                                        "widget_type": "TextHeading",
                                        "heading_level": 3
                                    },
                                    {
                                        "attribute_alias": "webservice_response__response_header",
                                        "width": "max",
                                        "height": "35%",
                                        "widget_type": "InputJson",
                                        "disabled": true,
                                        "hide_caption": true
                                    }
                                ]
                            },
                            {
                                "caption": "Request body",
                                "widgets": [
                                    {
                                        "attribute_alias": "http_body",
                                        "widget_type": "InputJson",
                                        "disabled": true,
                                        "height": "100%",
                                        "width": "100%",
                                        "hide_caption": true
                                    }
                                ]
                            },
                            {
                                "caption": "Response body",
                                "widgets": [
                                    {
                                        "attribute_alias": "webservice_response__response_body",
                                        "widget_type": "InputJson",
                                        "disabled": true,
                                        "height": "100%",
                                        "width": "100%",
                                        "hide_caption": true
                                    }
                                ]
                            }
                        ]
                    }
                ]
            },
            "ALIAS": "webservice_request",
            "DATA_ADDRESS": "etl_webservice_request"
        }
    ],
    "totals_rows": [],
    "filters": {
        "operator": "AND",
        "base_object_alias": "exface.Core.OBJECT",
        "conditions": [
            {
                "expression": "APP",
                "comparator": "=",
                "value": "0x11ebbc50679eacdabc50025041000001",
                "object_alias": "exface.Core.OBJECT"
            }
        ]
    },
    "rows_limit": null,
    "rows_offset": 0,
    "sorters": [
        {
            "attribute_alias": "CREATED_ON",
            "direction": "ASC"
        },
        {
            "attribute_alias": "UID",
            "direction": "ASC"
        }
    ]
}